{
  "product_id": "19089",
  "ratings": {
      "4": "1",
      "5": "1"
  },
  "recommended": {
      "false": "1",
      "true": "1"
  },
  "characteristics": {
      "Fit": {
          "id": 64059,
          "value": "4.0000000000000000"
      },
      "Length": {
          "id": 64060,
          "value": "3.5000000000000000"
      },
      "Comfort": {
          "id": 64061,
          "value": "5.0000000000000000"
      },
      "Quality": {
          "id": 64062,
          "value": "4.0000000000000000"
      }
  }
}